<?xml version="1.0" encoding="UTF-8"?>
<objects serializationModel="Studio.02.02.00">
	<object class="AudioFile" id="{28e1c1d8-7b67-4ddb-9046-bff067a3816e}">
		<property name="assetPath">
			<value>Enemies/spawn02.wav</value>
		</property>
		<property name="frequencyInKHz">
			<value>44.0999985</value>
		</property>
		<property name="channelCount">
			<value>2</value>
		</property>
		<property name="length">
			<value>7.3894331065759635</value>
		</property>
		<relationship name="masterAssetFolder">
			<destination>{d28682da-5472-47df-98b8-19164b24f0fc}</destination>
		</relationship>
	</object>
</objects>
